dailybasket_support/__init__.py
dailybasket_support/support_bridge.py
dailybasket_support/support_store.py
dailybasket_support/sync_sf_case_status.py
dailybasket_support_mithilesh-0.0.1.dist-info/METADATA
dailybasket_support_mithilesh-0.0.1.dist-info/WHEEL
dailybasket_support_mithilesh-0.0.1.dist-info/licenses/LICENSE
dailybasket_support_mithilesh-0.0.1.dist-info/RECORD
